Metadata-Version: 2.1
Name: single-line-diff
Version: 0.2.1
Summary: A package that can diff single lines
Home-page: https://gitlab.com/azuredown/single_line_diff
Author: Andrew Zuo
Author-email: andrew@andrewzuo.com
License: UNKNOWN
Platform: UNKNOWN
Requires-Python: >=3
License-File: LICENSE
